ampel/lsst/alert/ElasticcAlertSupplier.py
ampel/lsst/alert/LSSTAlertSupplier.py
ampel/lsst/alert/load/ElasticcDirAlertLoader.py
ampel/lsst/alert/load/ElasticcTrainingsetLoader.py
ampel/lsst/alert/load/HttpSchemaRepository.py
ampel/lsst/alert/load/KafkaAlertLoader.py
ampel/lsst/alert/load/MultiAvroAlertLoader.py
ampel/lsst/aux/LSSTDPFilter.py
ampel/lsst/aux/LSSTFPFilter.py
ampel/lsst/aux/LSSTObjFilter.py
ampel/lsst/ingest/LSSTCompilerOptions.py
ampel/lsst/ingest/LSSTDataPointShaper.py
ampel/lsst/ingest/LSSTMongoMuxer.py
ampel/lsst/t0/ReallySimpleLSSTFilter.py
ampel/lsst/t0/SimpleLSSTFilter.py
ampel/lsst/t1/LSSTT1Combiner.py
ampel/lsst/t2/T2GetAlertId.py
ampel/lsst/t2/T2GetAlertJournal.py
ampel/lsst/t2/T2GetDiaObject.py
ampel/lsst/template/ElasticcAlertConsumerTemplate.py
ampel/lsst/template/LSSTAlertConsumerTemplate.py
ampel/lsst/view/LSSTT2Tabulator.py
ampel/py.typed
conf/ampel-lsst/ampel.yml
ampel_lsst-0.8.6.dist-info/LICENSE
ampel_lsst-0.8.6.dist-info/METADATA
ampel_lsst-0.8.6.dist-info/WHEEL
ampel_lsst-0.8.6.dist-info/RECORD
