Metadata-Version: 2.1
Name: ampel-lsst
Version: 0.8.6
Summary: Legacy Survey of Space and Time support for the Ampel system
Home-page: https://ampelproject.github.io
License: BSD-3-Clause
Author: Marcus Fenner
Author-email: mf@physik.hu-berlinn.de
Maintainer: Marcus Fenner
Maintainer-email: mf@physik.hu-berlinn.de
Requires-Python: >=3.10,<3.12
Classifier: Development Status :: 3 - Alpha
Classifier: Intended Audience :: Science/Research
Classifier: License :: OSI Approved :: BSD License
Classifier: Programming Language :: Python :: 3
Classifier: Programming Language :: Python :: 3.10
Classifier: Programming Language :: Python :: 3.11
Classifier: Programming Language :: Python :: 3.9
Classifier: Topic :: Scientific/Engineering :: Astronomy
Classifier: Topic :: Scientific/Engineering :: Information Analysis
Classifier: Typing :: Typed
Requires-Dist: ampel-alerts (>=0.8.5,<0.9.0)
Requires-Dist: ampel-ztf[kafka] (>=0.8.5,<0.9.0)
Requires-Dist: astropy (>=5.0.2,<6.0.0)
Requires-Dist: fastavro (>=1.3.2,<2.0.0)
Project-URL: Repository, https://github.com/AmpelProject/Ampel-LSST
